mets_retriever/__init__.py
mets_retriever/cli.py
mets_retriever/mets_retriever.py
mets_retriever-0.2.2.dist-info/LICENSE
mets_retriever-0.2.2.dist-info/METADATA
mets_retriever-0.2.2.dist-info/WHEEL
mets_retriever-0.2.2.dist-info/entry_points.txt
mets_retriever-0.2.2.dist-info/top_level.txt
mets_retriever-0.2.2.dist-info/RECORD
