Metadata-Version: 2.1
Name: mets-retriever
Version: 0.2.2
Summary: Python library and CLI tool to download Archivematica METS files
Home-page: https://github.com/artefactual-labs/mets-retriever
Author: Artefactual Systems, Inc.
Author-email: info@artefactual.com
Project-URL: Bug Tracker, https://github.com/artefactual-labs/mets-retriever/issues
Classifier: Programming Language :: Python :: 3
Classifier: License :: OSI Approved :: Apache Software License
Classifier: Operating System :: OS Independent
Requires-Python: >=3.6
License-File: LICENSE
Requires-Dist: Click (>=8.0.4)
Requires-Dist: amclient (>=1.2.2)
Requires-Dist: SQLAlchemy (>=1.4.35)
